what_cli/__init__.py
what_cli/__main__.py
what_cli/matcher.py
what_cli/what.py
what_cli/entities/__init__.py
what_cli/entities/entity.py
what_cli/entities/file.py
what_cli/entities/preview.py
what_cli/entities/process.py
what_cli/entities/user.py
what_cli/fields/__init__.py
what_cli/fields/basic.py
what_cli/fields/code.py
what_cli/fields/containers.py
what_cli/fields/permissions.py
what_cli/fields/semantic.py
what_cli-1.0.3.dist-info/entry_points.txt
what_cli-1.0.3.dist-info/licenses/LICENSE
what_cli-1.0.3.dist-info/WHEEL
what_cli-1.0.3.dist-info/METADATA
what_cli-1.0.3.dist-info/RECORD
