Metadata-Version: 2.4
Name: what-cli
Version: 1.0.3
Summary: Right-click for the command line
Keywords: what,file,cli,util
Author-email: Rich Smith <rls@hwyl.org>
Requires-Python: >=3.12
License-Expression: GPL-3.0-or-later
Classifier: Programming Language :: Python
Classifier: Programming Language :: Python :: 3
License-File: LICENSE
Requires-Dist: ascii-magic >= 1.5
Requires-Dist: chardet >= 5.2.0
Requires-Dist: humanize >=  4.12.0
Requires-Dist: mutagen >= 1.47
Requires-Dist: pillow >= 11.2.0
Requires-Dist: psutil >= 7.0.0
Requires-Dist: pygments >= 2.19
Requires-Dist: pymediainfo >= 7.0
Requires-Dist: python-magic >= 0.4
Requires-Dist: rich >= 14.0.0
Requires-Dist: pytest >= 8.0 ; extra == "dev"
Requires-Dist: pytest-mock >= 3.12 ; extra == "dev"
Project-URL: Home, https://github.com/richsmith/what
Provides-Extra: dev
